{
  "rootObjects": [
    {
      "id": "__00001__",
      "name": null
    }
  ],
  "objects": {
    "__00001__": {
      "artists": "__00002__",
      "playlists": "__00003__",
      "users": "__00004__",
      "listeners": "__00005__"
    },
    "__00002__": {
      "0": "__00006__"
    },
    "__00003__": {},
    "__00004__": {},
    "__00005__": {},
    "__00006__": {
      "id": 1,
      "name": "David bowie",
      "country": "Usa",
      "albums": "__00007__"
    },
    "__00007__": {
      "0": "__00008__"
    },
    "__00008__": {
      "idArtist": 1,
      "id": 2,
      "name": "Album de David Bowie",
      "year": 2000,
      "tracks": "__00009__"
    },
    "__00009__": {
      "0": "__00010__"
    },
    "__00010__": {
      "idAlbum": 2,
      "id": 3,
      "name": "Stuck With U (with Justin Bieber)",
      "duration": 20,
      "genres": "__00011__",
      "lyrics": "Mmm\nHey, yeah\n(That's just for fun)\n(What?)\n(I'm stuck with you)\nAh\n\nI'm not one to stick around\nOne strike and you're out, baby\nDon't care if I sound crazy\nBut you never let me down, no, no\nThat's why when the sun's up, I'm stayin'\nStill layin' in your bed, singin'\n\nOoh, ooh, ooh, ooh\nGot all this time on my hands\nMight as well cancel our plans, yeah\nI could stay here for a lifetime\n\nSo, lock the door and throw out the key\nCan't fight this no more, it's just you and me\nAnd there's nothin' I, nothin' I, I can do\n...\n\n******* This Lyrics is NOT for Commercial use *******\n(1409620044221)"
    },
    "__00011__": {
      "0": "pop"
    }
  },
  "types": {
    "__00001__": "UNQfy",
    "__00002__": "Array",
    "__00003__": "Array",
    "__00004__": "Array",
    "__00005__": "Array",
    "__00006__": "Artist",
    "__00007__": "Array",
    "__00008__": "Album",
    "__00009__": "Array",
    "__00010__": "Track",
    "__00011__": "Array"
  }
}